{"GlobalPropertiesHash":"XbPm1yEMLr8WrchyMGMEAGmM7tbOuv9UjoRi8cuuKvs=","FingerprintPatternsHash":"gq3WsqcKBUGTSNle7RKKyXRIwh7M8ccEqOqYvIzoM04=","PropertyOverridesHash":"8ZRc1sGeVrPBx4lD717BgRaQekyh78QKV9SKsdt638U=","InputHashes":["\u002BeGZ4XrjGXJbp7YZf\u002BhT0KkecaNtHoPHNtIs2hIkC4g=","qhy\u002BGg5urw71EIBqw9zj7IDfcEjJQ\u002BpGZhrAlkmfjZ4=","U2M1d932xsz7ifhQ41rExcy5H/F084LBs1I\u002B59zaJJU=","1bp0YYu\u002ByM9QKAmkBkU0Q9UC5VljXQGlbWHgrbBIIfg="],"CachedAssets":{"1bp0YYu\u002ByM9QKAmkBkU0Q9UC5VljXQGlbWHgrbBIIfg=":{"Identity":"/Users/cindyfeng/pokemon-app/Server/wwwroot/Pokemon.png","SourceId":"pokemon-app","SourceType":"Discovered","ContentRoot":"/Users/cindyfeng/pokemon-app/Server/wwwroot/","BasePath":"_content/pokemon-app","RelativePath":"Pokemon#[.{fingerprint}]?.png","AssetKind":"All","AssetMode":"All","AssetRole":"Primary","AssetMergeBehavior":null,"AssetMergeSource":"","RelatedAsset":null,"AssetTraitName":null,"AssetTraitValue":null,"Fingerprint":"10micfflnw","Integrity":"4Zf0XmOC/P10aW2fRAVlU8v6hOyaZr/YvzdBNG4B960=","CopyToOutputDirectory":"Always","CopyToPublishDirectory":"PreserveNewest","OriginalItemSpec":"wwwroot/Pokemon.png","FileLength":16902,"LastWriteTime":"2025-07-26T00:30:24.9634886+00:00"},"U2M1d932xsz7ifhQ41rExcy5H/F084LBs1I\u002B59zaJJU=":{"Identity":"/Users/cindyfeng/pokemon-app/Server/wwwroot/index.html","SourceId":"pokemon-app","SourceType":"Discovered","ContentRoot":"/Users/cindyfeng/pokemon-app/Server/wwwroot/","BasePath":"_content/pokemon-app","RelativePath":"index#[.{fingerprint}]?.html","AssetKind":"All","AssetMode":"All","AssetRole":"Primary","AssetMergeBehavior":null,"AssetMergeSource":"","RelatedAsset":null,"AssetTraitName":null,"AssetTraitValue":null,"Fingerprint":"lobif9f0fi","Integrity":"W9Hp\u002BPrzDlrJdtYPaLSOrPkdnh02MJ7Kv4pbQtqiP1Y=","CopyToOutputDirectory":"Always","CopyToPublishDirectory":"PreserveNewest","OriginalItemSpec":"wwwroot/index.html","FileLength":468,"LastWriteTime":"2025-07-26T00:30:25.0273582+00:00"},"qhy\u002BGg5urw71EIBqw9zj7IDfcEjJQ\u002BpGZhrAlkmfjZ4=":{"Identity":"/Users/cindyfeng/pokemon-app/Server/wwwroot/assets/index-DvYV7pxf.css","SourceId":"pokemon-app","SourceType":"Discovered","ContentRoot":"/Users/cindyfeng/pokemon-app/Server/wwwroot/","BasePath":"_content/pokemon-app","RelativePath":"assets/index-DvYV7pxf#[.{fingerprint}]?.css","AssetKind":"All","AssetMode":"All","AssetRole":"Primary","AssetMergeBehavior":null,"AssetMergeSource":"","RelatedAsset":null,"AssetTraitName":null,"AssetTraitValue":null,"Fingerprint":"1ddr3p1u6i","Integrity":"ZfMS9Ig\u002B7KFdUF\u002BLUzFDDOTQMcRh4LaDGLdnGc5onjc=","CopyToOutputDirectory":"Always","CopyToPublishDirectory":"PreserveNewest","OriginalItemSpec":"wwwroot/assets/index-DvYV7pxf.css","FileLength":3664,"LastWriteTime":"2025-07-26T00:30:25.0273647+00:00"},"\u002BeGZ4XrjGXJbp7YZf\u002BhT0KkecaNtHoPHNtIs2hIkC4g=":{"Identity":"/Users/cindyfeng/pokemon-app/Server/wwwroot/assets/index-DVEyzHTz.js","SourceId":"pokemon-app","SourceType":"Discovered","ContentRoot":"/Users/cindyfeng/pokemon-app/Server/wwwroot/","BasePath":"_content/pokemon-app","RelativePath":"assets/index-DVEyzHTz#[.{fingerprint}]?.js","AssetKind":"All","AssetMode":"All","AssetRole":"Primary","AssetMergeBehavior":null,"AssetMergeSource":"","RelatedAsset":null,"AssetTraitName":null,"AssetTraitValue":null,"Fingerprint":"gq10478vn6","Integrity":"OLeN4RVHux7fj2xqjUeJ0ZMoiZndwRnRrpw6Frhj/HI=","CopyToOutputDirectory":"Always","CopyToPublishDirectory":"PreserveNewest","OriginalItemSpec":"wwwroot/assets/index-DVEyzHTz.js","FileLength":262028,"LastWriteTime":"2025-07-26T00:30:25.0273725+00:00"}},"CachedCopyCandidates":{}}